napari_mAIcrobe/__init__.py
napari_mAIcrobe/_compute_pickles.py
napari_mAIcrobe/_computecells.py
napari_mAIcrobe/_computelabel.py
napari_mAIcrobe/_filtercells.py
napari_mAIcrobe/_sample_data.py
napari_mAIcrobe/napari.yaml
napari_mAIcrobe/_tests/__init__.py
napari_mAIcrobe/_tests/analysis_test.py
napari_mAIcrobe/_tests/conftest.py
napari_mAIcrobe/_tests/sampledata_test.py
napari_mAIcrobe/_tests/segmentation_test.py
napari_mAIcrobe/mAIcrobe/__init__.py
napari_mAIcrobe/mAIcrobe/cellaverager.py
napari_mAIcrobe/mAIcrobe/cellcycleclassifier.py
napari_mAIcrobe/mAIcrobe/cellprocessing.py
napari_mAIcrobe/mAIcrobe/cells.py
napari_mAIcrobe/mAIcrobe/colocmanager.py
napari_mAIcrobe/mAIcrobe/mask.py
napari_mAIcrobe/mAIcrobe/reports.py
napari_mAIcrobe/mAIcrobe/segments.py
napari_mAIcrobe/mAIcrobe/unet.py
napari_maicrobe-0.0.5.dist-info/licenses/LICENSE
napari_maicrobe-0.0.5.dist-info/METADATA
napari_maicrobe-0.0.5.dist-info/WHEEL
napari_maicrobe-0.0.5.dist-info/entry_points.txt
napari_maicrobe-0.0.5.dist-info/top_level.txt
napari_maicrobe-0.0.5.dist-info/RECORD
