Metadata-Version: 2.4
Name: napari-mAIcrobe
Version: 0.0.5
Summary: mAIcrobe
Home-page: https://github.com/HenriquesLab/napari-mAIcrobe
Author: António Brito
Author-email: antmsbrito95@gmail.com
License: BSD-3-Clause
Project-URL: Bug Tracker, https://github.com/HenriquesLab/mAIcrobe/issues
Project-URL: Documentation, https://github.com/HenriquesLab/mAIcrobe#README.md
Project-URL: Source Code, https://github.com/HenriquesLab/mAIcrobe
Project-URL: User Support, https://github.com/HenriquesLab/mAIcrobe/issues
Classifier: Development Status :: 2 - Pre-Alpha
Classifier: Framework :: napari
Classifier: Intended Audience :: Developers
Classifier: License :: OSI Approved :: BSD License
Classifier: Operating System :: OS Independent
Classifier: Programming Language :: Python
Classifier: Programming Language :: Python :: 3
Classifier: Programming Language :: Python :: 3 :: Only
Classifier: Programming Language :: Python :: 3.10
Classifier: Programming Language :: Python :: 3.11
Classifier: Topic :: Scientific/Engineering :: Image Processing
Requires-Python: >=3.8
License-File: LICENSE
Requires-Dist: numpy<2.0
Requires-Dist: magicgui>=0.10.0
Requires-Dist: napari[all]
Requires-Dist: tensorflow<=2.15.0
Requires-Dist: napari-skimage-regionprops
Requires-Dist: stardist-napari==2022.12.6
Requires-Dist: scikit-learn
Requires-Dist: scikit-image==0.20.0
Requires-Dist: pandas
Requires-Dist: cellpose==3.1.1.1
Provides-Extra: testing
Requires-Dist: tox; extra == "testing"
Requires-Dist: pytest; extra == "testing"
Requires-Dist: pytest-cov; extra == "testing"
Requires-Dist: pytest-qt; extra == "testing"
Requires-Dist: napari; extra == "testing"
Requires-Dist: pyqt5; extra == "testing"
Dynamic: license-file
